src/__init__.py
src/scroll.py
src/witcher.py
witcher_cli-1.0.8.dist-info/METADATA
witcher_cli-1.0.8.dist-info/WHEEL
witcher_cli-1.0.8.dist-info/entry_points.txt
witcher_cli-1.0.8.dist-info/top_level.txt
witcher_cli-1.0.8.dist-info/RECORD
